ramman/__init__.py
ramman/cli.py
ramman/ramman.py
ramman/utils.py
ramman-0.1.2.dist-info/METADATA
ramman-0.1.2.dist-info/WHEEL
ramman-0.1.2.dist-info/entry_points.txt
ramman-0.1.2.dist-info/top_level.txt
ramman-0.1.2.dist-info/RECORD
