Metadata-Version: 2.1
Name: ramman
Version: 0.1.2
Summary: Heman tiny client
Home-page: http://www.somenergia.coop
Author: Somenergia, coop
Author-email: UNKNOWN
License: MIT
Platform: UNKNOWN
Requires-Dist: requests
Requires-Dist: click
